robox/__init__.py
robox/annotations.py
robox/autoenum.py
robox/box/__init__.py
robox/box/builder.py
robox/box/checkers.py
robox/box/code.py
robox/box/conftest.py
robox/box/contest/__init__.py
robox/box/contest/build_contest_statements.py
robox/box/contest/contest_package.py
robox/box/contest/contest_utils.py
robox/box/contest/main.py
robox/box/contest/schema.py
robox/box/contest/statements.py
robox/box/creation.py
robox/box/download.py
robox/box/environment.py
robox/box/generators.py
robox/box/generators_test.py
robox/box/main.py
robox/box/package.py
robox/box/packaging/boca/packager.py
robox/box/packaging/contest_main.py
robox/box/packaging/main.py
robox/box/packaging/packager.py
robox/box/packaging/polygon/packager.py
robox/box/packaging/polygon/test.py
robox/box/packaging/polygon/xml_schema.py
robox/box/presets/__init__.py
robox/box/presets/schema.py
robox/box/schema.py
robox/box/solutions.py
robox/box/solutions_test.py
robox/box/statements/__init__.py
robox/box/statements/build_statements.py
robox/box/statements/builders.py
robox/box/statements/joiners.py
robox/box/statements/latex.py
robox/box/statements/latex_jinja.py
robox/box/statements/schema.py
robox/box/stresses.py
robox/box/testcases.py
robox/box/validators.py
robox/box/validators_test.py
robox/checker.py
robox/clone.py
robox/config.py
robox/conftest.py
robox/console.py
robox/create.py
robox/edit.py
robox/grading/__init__.py
robox/grading/caching.py
robox/grading/judge/__init__.py
robox/grading/judge/cacher.py
robox/grading/judge/digester.py
robox/grading/judge/sandbox.py
robox/grading/judge/sandboxes/__init__.py
robox/grading/judge/sandboxes/isolate.py
robox/grading/judge/sandboxes/stupid_sandbox.py
robox/grading/judge/storage.py
robox/grading/judge/test.py
robox/grading/judge/testiso.py
robox/grading/steps.py
robox/grading_utils.py
robox/hydration.py
robox/main.py
robox/metadata.py
robox/providers/__init__.py
robox/providers/codeforces.py
robox/providers/provider.py
robox_io-0.3.8.dist-info/LICENSE
robox_io-0.3.8.dist-info/METADATA
robox_io-0.3.8.dist-info/WHEEL
robox_io-0.3.8.dist-info/entry_points.txt
robox_io-0.3.8.dist-info/RECORD
